niworkflows/__about__.py
niworkflows/__init__.py
niworkflows/_version.py
niworkflows/conftest.py
niworkflows/testing.py
niworkflows/anat/__init__.py
niworkflows/anat/ants.py
niworkflows/anat/coregistration.py
niworkflows/anat/freesurfer.py
niworkflows/anat/skullstrip.py
niworkflows/anat/tests/__init__.py
niworkflows/anat/tests/test_ants.py
niworkflows/cli/__init__.py
niworkflows/cli/boldref.py
niworkflows/data/__init__.py
niworkflows/data/antsBrainExtractionNoLaplacian_precise.json
niworkflows/data/antsBrainExtractionNoLaplacian_testing.json
niworkflows/data/antsBrainExtraction_precise.json
niworkflows/data/antsBrainExtraction_testing.json
niworkflows/data/boldref-mni_registration_precise_000.json
niworkflows/data/boldref-mni_registration_precise_001.json
niworkflows/data/boldref-mni_registration_precise_002.json
niworkflows/data/boldref-mni_registration_testing_000.json
niworkflows/data/boldref-mni_registration_testing_001.json
niworkflows/data/boldref-mni_registration_testing_002.json
niworkflows/data/epi_atlasbased_brainmask.json
niworkflows/data/itkIdentityTransform.txt
niworkflows/data/nipreps.json
niworkflows/data/petref-mni_registration_precise_000.json
niworkflows/data/sentinel.nii.gz
niworkflows/data/t1w-mni_registration_fast_000.json
niworkflows/data/t1w-mni_registration_precise_000.json
niworkflows/data/t1w-mni_registration_precise_001.json
niworkflows/data/t1w-mni_registration_precise_002.json
niworkflows/data/t1w-mni_registration_testing_000.json
niworkflows/data/t1w-mni_registration_testing_001.json
niworkflows/data/t1w-mni_registration_testing_002.json
niworkflows/data/tests/crashfile.txt
niworkflows/dwi/__init__.py
niworkflows/engine/__init__.py
niworkflows/engine/plugin.py
niworkflows/engine/splicer.py
niworkflows/engine/workflows.py
niworkflows/engine/tests/__init__.py
niworkflows/engine/tests/test_plugin.py
niworkflows/engine/tests/test_splicer.py
niworkflows/engine/tests/test_workflows.py
niworkflows/func/__init__.py
niworkflows/func/util.py
niworkflows-1.14.4.dist-info/METADATA
niworkflows-1.14.4.dist-info/WHEEL
niworkflows-1.14.4.dist-info/entry_points.txt
niworkflows-1.14.4.dist-info/licenses/LICENSE
niworkflows-1.14.4.dist-info/RECORD
