Metadata-Version: 2.4
Name: niworkflows
Version: 1.14.4
Summary: NeuroImaging Workflows provides processing tools for magnetic resonance images of the brain.
Project-URL: Bug Tracker, https://github.com/nipreps/niworkflows/issues
Project-URL: Documentation, https://www.nipreps.org/niworkflows
Project-URL: GitHub, https://github.com/nipreps/niworkflows
Project-URL: Homepage, https://www.nipreps.org
Project-URL: Source Code, https://github.com/nipreps/niworkflows
Project-URL: Zenodo, https://doi.org/10.5281/zenodo.2650331
Author-email: The NiPreps Developers <nipreps@gmail.com>
License:                                  Apache License
License-File: LICENSE
Classifier: Development Status :: 4 - Beta
Classifier: Intended Audience :: Science/Research
Classifier: License :: OSI Approved :: Apache Software License
Classifier: Programming Language :: Python :: 3.9
Classifier: Programming Language :: Python :: 3.10
Classifier: Programming Language :: Python :: 3.11
Classifier: Programming Language :: Python :: 3.12
Classifier: Programming Language :: Python :: 3.13
Classifier: Topic :: Scientific/Engineering :: Image Recognition
Requires-Python: >=3.9
Requires-Dist: acres
Requires-Dist: attrs>=20.1
Requires-Dist: jinja2>=3
Requires-Dist: looseversion
Requires-Dist: matplotlib>=3.5
Requires-Dist: nibabel>=3.0
Requires-Dist: nilearn>=0.8
Requires-Dist: nipype>=1.8.5
Requires-Dist: nitransforms>=22.0.0
Requires-Dist: numpy>=1.20
Requires-Dist: packaging
Requires-Dist: pandas>=1.2
Requires-Dist: pybids>=0.15.1
Requires-Dist: pyyaml>=5.4
Requires-Dist: scikit-image>=0.18
Requires-Dist: scipy>=1.8
Requires-Dist: seaborn>=0.11
Requires-Dist: svgutils>=0.3.4
Requires-Dist: templateflow>=23.1
Requires-Dist: transforms3d>=0.4
Provides-Extra: all
Requires-Dist: coverage[toml]>=5.2.1; extra == 'all'
Requires-Dist: flake8>=3.7.0; extra == 'all'
Requires-Dist: furo; extra == 'all'
Requires-Dist: pydot>=1.2.3; extra == 'all'
Requires-Dist: pydotplus; extra == 'all'
Requires-Dist: pyntcloud; extra == 'all'
Requires-Dist: pytest-cov>=2.11; extra == 'all'
Requires-Dist: pytest-env; extra == 'all'
Requires-Dist: pytest-xdist>=2.5; extra == 'all'
Requires-Dist: pytest-xvfb>=2; extra == 'all'
Requires-Dist: pytest>=6; extra == 'all'
Requires-Dist: sphinx; extra == 'all'
Requires-Dist: sphinxcontrib-apidoc; extra == 'all'
Requires-Dist: sphinxcontrib-napoleon; extra == 'all'
Provides-Extra: doc
Requires-Dist: furo; extra == 'doc'
Requires-Dist: pydot>=1.2.3; extra == 'doc'
Requires-Dist: pydotplus; extra == 'doc'
Requires-Dist: sphinx; extra == 'doc'
Requires-Dist: sphinxcontrib-apidoc; extra == 'doc'
Requires-Dist: sphinxcontrib-napoleon; extra == 'doc'
Provides-Extra: docs
Requires-Dist: furo; extra == 'docs'
Requires-Dist: pydot>=1.2.3; extra == 'docs'
Requires-Dist: pydotplus; extra == 'docs'
Requires-Dist: sphinx; extra == 'docs'
Requires-Dist: sphinxcontrib-apidoc; extra == 'docs'
Requires-Dist: sphinxcontrib-napoleon; extra == 'docs'
Provides-Extra: pointclouds
Requires-Dist: pyntcloud; extra == 'pointclouds'
Provides-Extra: style
Requires-Dist: flake8>=3.7.0; extra == 'style'
Provides-Extra: tests
Requires-Dist: coverage[toml]>=5.2.1; extra == 'tests'
Requires-Dist: pytest-cov>=2.11; extra == 'tests'
Requires-Dist: pytest-env; extra == 'tests'
Requires-Dist: pytest-xdist>=2.5; extra == 'tests'
Requires-Dist: pytest-xvfb>=2; extra == 'tests'
Requires-Dist: pytest>=6; extra == 'tests'
